pyMKL2/MKLutils.py
pyMKL2/__init__.py
pyMKL2/loadMKL.py
pyMKL2/pardisoInterface.py
pyMKL2/pardisoSolver.py
pyMKL2-0.0.4.dist-info/LICENSE
pyMKL2-0.0.4.dist-info/METADATA
pyMKL2-0.0.4.dist-info/WHEEL
pyMKL2-0.0.4.dist-info/top_level.txt
pyMKL2-0.0.4.dist-info/RECORD
